ESN/ML.py
ESN/__init__.py
ESN-0.0.1.dist-info/LICENSE
ESN-0.0.1.dist-info/METADATA
ESN-0.0.1.dist-info/WHEEL
ESN-0.0.1.dist-info/top_level.txt
ESN-0.0.1.dist-info/RECORD
