Metadata-Version: 2.1
Name: ESN
Version: 0.0.1
Summary: Multiple Layer ESN
Home-page: https://github.com/Xeeshanmalik/deep_ml_esn
Author: Zeeshan Malik
Author-email: doctordotmalik@gmail.com
License: UNKNOWN
Platform: UNKNOWN
